{"nombre_institucion":"PETR\u00d3LEOS MEXICANOS (CORPORATIVO) en proceso de reestructuraci\u00f3n","sector_presupuestal":"Energ\u00eda","siglas":"PEMEX","fecha_actualizacion":"18\/07\/2014","numero_contrato":"4200127175","unidad_administrativa":"GERENCIA DE ABASTECIMIENTO DE BIENES Y SERVICIOS","procedimiento_contratacion":"ADJUDICACION DIRECTA","denominacion_asignado":"ORGANIZACI\u00d3N PAPELERA OMEGA, S.A. DE C. V.","fecha_contrato":"15\/07\/2013","objeto_contrato":"ADQUISICI\u00d3N DE PAPELER\u00cdA GENERAL PARA LA SUBGERENCIA DE SERVICIOS JURIDICOS REGION PACIFICO OCCIDENTE","monto_contrato":"$10840.88","moneda":"PESOS","fecha_inicio":"15\/07\/2013","fecha_fin":"23\/08\/2013","documento":"N\/A","clave_institucion":18572,"url_info":"http:\/\/portaltransparencia.gob.mx\/pot\/contrataciones\/consultarContrato.do?method=consultaContrato&id.idContrato=4200127175&_idDependencia=18572","_id":{"$id":"53d6726e4d5fa3ea4c8b496d"}}