{"nombre_institucion":"COMISI\u00d3N FEDERAL DE ELECTRICIDAD","sector_presupuestal":"Energ\u00eda","siglas":"CFE","fecha_actualizacion":"07\/07\/2014","numero_contrato":"700407788","unidad_administrativa":"SUPERINTENDENCIA CENTRAL TERMOEL\u00c9CTRICA CARB\u00d3N II","procedimiento_contratacion":"ADJUDICACION DIRECTA","denominacion_asignado":"MAQUINADOS CAMOSA, S.A. DE C.V.","fecha_contrato":"22\/01\/2013","objeto_contrato":"Accesorios y Herramientas para Equipo","monto_contrato":"$166250","moneda":"PESOS","fecha_inicio":"23\/01\/2013","fecha_fin":"08\/03\/2013","documento":"N\/A","clave_institucion":18164,"url_info":"http:\/\/portaltransparencia.gob.mx\/pot\/contrataciones\/consultarContrato.do?method=consultaContrato&id.idContrato=700407788&_idDependencia=18164","_id":{"$id":"53d5a04188d6c695138b4d0c"}}