{"nombre_institucion":"COMISI\u00d3N FEDERAL DE ELECTRICIDAD","sector_presupuestal":"Energ\u00eda","siglas":"CFE","fecha_actualizacion":"07\/07\/2014","numero_contrato":"700407176","unidad_administrativa":"GERENCIA REGIONAL DE TRANSMISI\u00d3N NORESTE","procedimiento_contratacion":"LICITACION PUBLICA NACIONAL","denominacion_asignado":"SENSA CONTROL DIGITAL, S.A. DE C.V.","fecha_contrato":"27\/12\/2012","objeto_contrato":"Refacciones para Equipo Electr\u00f3nico y de Comunicaci\u00f3n","monto_contrato":"$740624","moneda":"PESOS","fecha_inicio":"27\/12\/2012","fecha_fin":"26\/04\/2014","documento":"N\/A","clave_institucion":18164,"url_info":"http:\/\/portaltransparencia.gob.mx\/pot\/contrataciones\/consultarContrato.do?method=consultaContrato&id.idContrato=700407176&_idDependencia=18164","_id":{"$id":"53d59e7a88d6c695138b4b60"}}