{"nombre_institucion":"COMISI\u00d3N FEDERAL DE ELECTRICIDAD","sector_presupuestal":"Energ\u00eda","siglas":"CFE","fecha_actualizacion":"07\/07\/2014","numero_contrato":"700406325","unidad_administrativa":"DEPARTAMENTO DE ABASTECIMIENTOS","procedimiento_contratacion":"INVITACION A TRES PERSONAS","denominacion_asignado":"TECNATOM, S.A.","fecha_contrato":"15\/01\/2013","objeto_contrato":"Equipo y Aparatos para Laboratorio","monto_contrato":"$1322905","moneda":"PESOS","fecha_inicio":"30\/01\/2013","fecha_fin":"05\/11\/2013","documento":"N\/A","clave_institucion":18164,"url_info":"http:\/\/portaltransparencia.gob.mx\/pot\/contrataciones\/consultarContrato.do?method=consultaContrato&id.idContrato=700406325&_idDependencia=18164","_id":{"$id":"53d59b9488d6c695138b4913"}}