{"nombre_institucion":"COMISI\u00d3N FEDERAL DE ELECTRICIDAD","sector_presupuestal":"Energ\u00eda","siglas":"CFE","fecha_actualizacion":"07\/07\/2014","numero_contrato":"700408550","unidad_administrativa":"SUPERINTENDENCIA CENTRAL TERMOEL\u00c9CTRICA PDTE. JU\u00c1REZ (TIJUANA)","procedimiento_contratacion":"INVITACION A TRES PERSONAS","denominacion_asignado":"AMBIENT PLUS DE MEXICO, S.A DE C.V.","fecha_contrato":"12\/02\/2013","objeto_contrato":"Equipo y Aparatos para Laboratorio","monto_contrato":"$1710000","moneda":"PESOS","fecha_inicio":"12\/02\/2013","fecha_fin":"14\/03\/2013","documento":"N\/A","clave_institucion":18164,"url_info":"http:\/\/portaltransparencia.gob.mx\/pot\/contrataciones\/consultarContrato.do?method=consultaContrato&id.idContrato=700408550&_idDependencia=18164","_id":{"$id":"53d5a23188d6c695138b4f69"}}