{"nombre_institucion":"COMISI\u00d3N FEDERAL DE ELECTRICIDAD","sector_presupuestal":"Energ\u00eda","siglas":"CFE","fecha_actualizacion":"07\/07\/2014","numero_contrato":"700409565","unidad_administrativa":"GERENCIA DIVISIONAL DE DISTRIBUCI\u00d3N JALISCO","procedimiento_contratacion":"INVITACION A TRES PERSONAS","denominacion_asignado":"MAYOREO ELECTROMECANICO, S.A. DE C.V.","fecha_contrato":"26\/02\/2013","objeto_contrato":"Apartarrayos","monto_contrato":"$227255","moneda":"PESOS","fecha_inicio":"26\/02\/2013","fecha_fin":"26\/05\/2013","documento":"N\/A","clave_institucion":18164,"url_info":"http:\/\/portaltransparencia.gob.mx\/pot\/contrataciones\/consultarContrato.do?method=consultaContrato&id.idContrato=700409565&_idDependencia=18164","_id":{"$id":"53d5a48a88d6c695138b529c"}}