{"nombre_institucion":"COMISI\u00d3N FEDERAL DE ELECTRICIDAD","sector_presupuestal":"Energ\u00eda","siglas":"CFE","fecha_actualizacion":"07\/07\/2014","numero_contrato":"700409424","unidad_administrativa":"SUPERINTENDENCIA ZONA MONCLOVA","procedimiento_contratacion":"ADJUDICACION DIRECTA","denominacion_asignado":"F G ELECTRICAL REPRESENTATIVES, S.A. DE C.V.","fecha_contrato":"22\/02\/2013","objeto_contrato":"Conectadores","monto_contrato":"$18318","moneda":"PESOS","fecha_inicio":"22\/02\/2013","fecha_fin":"11\/03\/2013","documento":"N\/A","clave_institucion":18164,"url_info":"http:\/\/portaltransparencia.gob.mx\/pot\/contrataciones\/consultarContrato.do?method=consultaContrato&id.idContrato=700409424&_idDependencia=18164","_id":{"$id":"53d5a44188d6c695138b5237"}}