{"nombre_institucion":"COMISI\u00d3N FEDERAL DE ELECTRICIDAD","sector_presupuestal":"Energ\u00eda","siglas":"CFE","fecha_actualizacion":"07\/07\/2014","numero_contrato":"700415184","unidad_administrativa":"SUPERINTENDENCIA ZONA CHIHUAHUA","procedimiento_contratacion":"ADJUDICACION DIRECTA","denominacion_asignado":"PRO-TECH SEGURIDAD INDUSTRIAL Y MARITIMA, S.A. DE C.V.","fecha_contrato":"03\/06\/2013","objeto_contrato":"Equipo de Control, Protecci\u00f3n y Medici\u00f3n","monto_contrato":"$54472","moneda":"PESOS","fecha_inicio":"03\/06\/2013","fecha_fin":"16\/06\/2013","documento":"N\/A","clave_institucion":18164,"url_info":"http:\/\/portaltransparencia.gob.mx\/pot\/contrataciones\/consultarContrato.do?method=consultaContrato&id.idContrato=700415184&_idDependencia=18164","_id":{"$id":"53d5b31988d6c695138b62bd"}}