{"nombre_institucion":"COMISI\u00d3N FEDERAL DE ELECTRICIDAD","sector_presupuestal":"Energ\u00eda","siglas":"CFE","fecha_actualizacion":"07\/07\/2014","numero_contrato":"700405551","unidad_administrativa":"SUPERINTENDENCIA CENTRAL DI\u00c9SEL EL\u00c9CTRICA GRAL. AGUST\u00cdN OLACHEA AVIL\u00c9S (PUERTO SAN CARLOS)","procedimiento_contratacion":"INVITACION A TRES PERSONAS","denominacion_asignado":"MAQUINARIA INDUSTRIAL MODERNA, S.A. DE C.V.","fecha_contrato":"15\/12\/2012","objeto_contrato":"Refacciones para Maquinaria y Equipo El\u00e9ctrico","monto_contrato":"$626682","moneda":"PESOS","fecha_inicio":"15\/12\/2012","fecha_fin":"27\/12\/2012","documento":"N\/A","clave_institucion":18164,"url_info":"http:\/\/portaltransparencia.gob.mx\/pot\/contrataciones\/consultarContrato.do?method=consultaContrato&id.idContrato=700405551&_idDependencia=18164","_id":{"$id":"53d599a588d6c695138b4701"}}