{"nombre_institucion":"COMISI\u00d3N FEDERAL DE ELECTRICIDAD","sector_presupuestal":"Energ\u00eda","siglas":"CFE","fecha_actualizacion":"07\/07\/2014","numero_contrato":"700413111","unidad_administrativa":"SUPERINTENDENCIA CENTRAL DI\u00c9SEL EL\u00c9CTRICA GRAL. AGUST\u00cdN OLACHEA AVIL\u00c9S (PUERTO SAN CARLOS)","procedimiento_contratacion":"INVITACION A TRES PERSONAS","denominacion_asignado":"SMAR INDUSTRIAL AUTOMATION, S.A. DE C.V.","fecha_contrato":"30\/04\/2013","objeto_contrato":"Refacciones para Equipo Electr\u00f3nico y de Comunicaci\u00f3n","monto_contrato":"$353753","moneda":"PESOS","fecha_inicio":"30\/04\/2013","fecha_fin":"08\/07\/2013","documento":"N\/A","clave_institucion":18164,"url_info":"http:\/\/portaltransparencia.gob.mx\/pot\/contrataciones\/consultarContrato.do?method=consultaContrato&id.idContrato=700413111&_idDependencia=18164","_id":{"$id":"53d5ad8d88d6c695138b5d0c"}}