{"nombre_institucion":"COMISI\u00d3N FEDERAL DE ELECTRICIDAD","sector_presupuestal":"Energ\u00eda","siglas":"CFE","fecha_actualizacion":"07\/07\/2014","numero_contrato":"700406654","unidad_administrativa":"RESIDENCIA DE CONSTRUCCI\u00d3N Y SUPERVISI\u00d3N DE PROYECTOS DE SE Y LT CENTRO","procedimiento_contratacion":"ADJUDICACION DIRECTA","denominacion_asignado":"TIENDAS CHEDRAUI, S.A. DE C.V.","fecha_contrato":"19\/12\/2012","objeto_contrato":"Art\u00edculos Diversos de Limpieza, Seguridad e Higi\u00e9ne","monto_contrato":"$39892","moneda":"PESOS","fecha_inicio":"19\/12\/2012","fecha_fin":"21\/12\/2012","documento":"N\/A","clave_institucion":18164,"url_info":"http:\/\/portaltransparencia.gob.mx\/pot\/contrataciones\/consultarContrato.do?method=consultaContrato&id.idContrato=700406654&_idDependencia=18164","_id":{"$id":"53d59cb688d6c695138b49f2"}}