{"nombre_institucion":"COMISI\u00d3N FEDERAL DE ELECTRICIDAD","sector_presupuestal":"Energ\u00eda","siglas":"CFE","fecha_actualizacion":"07\/07\/2014","numero_contrato":"700414795","unidad_administrativa":"SUPERINTENDENCIA CENTRAL TERMOEL\u00c9CTRICA ADOLFO L\u00d3PEZ MATEOS (TUXPAN)","procedimiento_contratacion":"ADJUDICACION DIRECTA","denominacion_asignado":"INFRA, S.A. DE C.V.","fecha_contrato":"24\/05\/2013","objeto_contrato":"Sustancias y Productos Qu\u00edmicos","monto_contrato":"$19804","moneda":"PESOS","fecha_inicio":"25\/05\/2013","fecha_fin":"28\/06\/2013","documento":"N\/A","clave_institucion":18164,"url_info":"http:\/\/portaltransparencia.gob.mx\/pot\/contrataciones\/consultarContrato.do?method=consultaContrato&id.idContrato=700414795&_idDependencia=18164","_id":{"$id":"53d5b1fb88d6c695138b61b5"}}