{"nombre_institucion":"COMISI\u00d3N FEDERAL DE ELECTRICIDAD","sector_presupuestal":"Energ\u00eda","siglas":"CFE","fecha_actualizacion":"07\/07\/2014","numero_contrato":"700410525","unidad_administrativa":"GERENCIA DIVISIONAL DE DISTRIBUCI\u00d3N VALLE DE M\u00c9XICO CENTRO","procedimiento_contratacion":"LICITACION PUBLICA NACIONAL","denominacion_asignado":"GENERAL CABLE DE MEXICO S.A. DE C.V.","fecha_contrato":"27\/03\/2013","objeto_contrato":"Alambre y Cable Conductor Desnudo","monto_contrato":"$17925360","moneda":"PESOS","fecha_inicio":"27\/03\/2013","fecha_fin":"31\/12\/2013","documento":"N\/A","clave_institucion":18164,"url_info":"http:\/\/portaltransparencia.gob.mx\/pot\/contrataciones\/consultarContrato.do?method=consultaContrato&id.idContrato=700410525&_idDependencia=18164","_id":{"$id":"53d5a71588d6c695138b556b"}}