{"nombre_institucion":"COMISI\u00d3N FEDERAL DE ELECTRICIDAD","sector_presupuestal":"Energ\u00eda","siglas":"CFE","fecha_actualizacion":"07\/07\/2014","numero_contrato":"700405136","unidad_administrativa":"SUBGERENCIA DE GENERACI\u00d3N HIDROEL\u00c9CTRICA GRIJALVA","procedimiento_contratacion":"ADJUDICACION DIRECTA","denominacion_asignado":"BORDADOS MICHEL , S.A DE C.V.","fecha_contrato":"10\/12\/2012","objeto_contrato":"Ropa de Trabajo para Caballero","monto_contrato":"$81642","moneda":"PESOS","fecha_inicio":"11\/12\/2012","fecha_fin":"25\/12\/2012","documento":"N\/A","clave_institucion":18164,"url_info":"http:\/\/portaltransparencia.gob.mx\/pot\/contrataciones\/consultarContrato.do?method=consultaContrato&id.idContrato=700405136&_idDependencia=18164","_id":{"$id":"53d598ce88d6c695138b45cb"}}