{"nombre_institucion":"COMISI\u00d3N FEDERAL DE ELECTRICIDAD","sector_presupuestal":"Energ\u00eda","siglas":"CFE","fecha_actualizacion":"07\/07\/2014","numero_contrato":"700416266","unidad_administrativa":"SUPERINTENDENCIA CENTRAL TERMOEL\u00c9CTRICA GUADALUPE VICTORIA","procedimiento_contratacion":"ADJUDICACION DIRECTA","denominacion_asignado":"NASA 2000, S.A. DE C.V.","fecha_contrato":"25\/06\/2013","objeto_contrato":"Equipo de Control, Protecci\u00f3n y Medici\u00f3n","monto_contrato":"$69999","moneda":"PESOS","fecha_inicio":"26\/06\/2013","fecha_fin":"25\/08\/2013","documento":"N\/A","clave_institucion":18164,"url_info":"http:\/\/portaltransparencia.gob.mx\/pot\/contrataciones\/consultarContrato.do?method=consultaContrato&id.idContrato=700416266&_idDependencia=18164","_id":{"$id":"53d5b63688d6c695138b6573"}}