{"nombre_institucion":"COMISI\u00d3N FEDERAL DE ELECTRICIDAD","sector_presupuestal":"Energ\u00eda","siglas":"CFE","fecha_actualizacion":"07\/07\/2014","numero_contrato":"9100004177","unidad_administrativa":"GERENCIA DIVISIONAL DE DISTRIBUCI\u00d3N GOLFO NORTE","procedimiento_contratacion":"LICITACION PUBLICA NACIONAL","denominacion_asignado":"Electrocontrol Regiomontano, S.A. de C.V.","fecha_contrato":"28\/02\/2007","objeto_contrato":"Conectadores","monto_contrato":"$6152265","moneda":"PESOS","fecha_inicio":"05\/03\/2007","fecha_fin":"24\/04\/2007","documento":"N\/A","clave_institucion":18164,"url_info":"http:\/\/portaltransparencia.gob.mx\/pot\/contrataciones\/consultarContrato.do?method=consultaContrato&id.idContrato=9100004177&_idDependencia=18164","_id":{"$id":"53d7069588d6c68b398b4642"}}