{"nombre_institucion":"COMISI\u00d3N FEDERAL DE ELECTRICIDAD","sector_presupuestal":"Energ\u00eda","siglas":"CFE","fecha_actualizacion":"07\/07\/2014","numero_contrato":"9100012200","unidad_administrativa":"GERENCIA DIVISIONAL DE DISTRIBUCI\u00d3N CENTRO SUR","procedimiento_contratacion":"INVITACION A TRES PERSONAS","denominacion_asignado":"ECISA CONSTRUCCIONES, S.A. DE C.V.","fecha_contrato":"20\/02\/2012","objeto_contrato":"Postes de Concreto","monto_contrato":"$1837976","moneda":"PESOS","fecha_inicio":"20\/02\/2012","fecha_fin":"05\/04\/2012","documento":"N\/A","clave_institucion":18164,"url_info":"http:\/\/portaltransparencia.gob.mx\/pot\/contrataciones\/consultarContrato.do?method=consultaContrato&id.idContrato=9100012200&_idDependencia=18164","_id":{"$id":"53d714d688d6c68b398b4b61"}}