{"nombre_institucion":"INSTITUTO MEXICANO DEL PETROLEO","sector_presupuestal":"Energ\u00eda","siglas":"IMP","fecha_actualizacion":"08\/07\/2014","numero_contrato":"2008000342","unidad_administrativa":"DIRECTOR REGIONAL SUR","procedimiento_contratacion":"ADJUDICACION DIRECTA","denominacion_asignado":"ESPINO HERNANDEZ JOSE LUIS","fecha_contrato":"01\/02\/2008","objeto_contrato":"CONTRATACION DE INSTRUCTOR PARA IMPARTIR SENSIBILIZACION Y TRABAJO EN EQUIPO DE LA PLANTA HIDROS DE GASOLEOS DEL PROGRAMA DE CAPACITACION.","monto_contrato":"$7992","moneda":"PESOS","fecha_inicio":"01\/02\/2008","fecha_fin":"11\/02\/2008","documento":"N\/A","clave_institucion":18474,"url_info":"http:\/\/portaltransparencia.gob.mx\/pot\/contrataciones\/consultarContrato.do?method=consultaContrato&id.idContrato=2008000342&_idDependencia=18474"}