{"nombre_institucion":"INSTITUTO MEXICANO DEL PETROLEO","sector_presupuestal":"Energ\u00eda","siglas":"IMP","fecha_actualizacion":"08\/07\/2014","numero_contrato":"2008001914","unidad_administrativa":"DIRECTOR CORPORATIVO DE FINANZAS Y ADMINISTRACION","procedimiento_contratacion":"ADJUDICACION DIRECTA","denominacion_asignado":"SELEE CORPORATION","fecha_contrato":"09\/05\/2008","objeto_contrato":"PANELES DE CERAMICA (MONOLITOS TIPO ESPUMA DE ALFA-ALUMINA, CON 0.48&quot; DE DIAMETRO X 0.50&quot; DE ESPESOR, 45PPI (POROS POR PULGADO LINEAL) CON MANGA (SLEEVED). ALPHA-ALUMINA FOAM MONOLITHS 0.48&quot; DIAMETER X 0.50&quot; THICK 45 PPI.","monto_contrato":"$10157.9","moneda":"PESOS","fecha_inicio":"09\/05\/2008","fecha_fin":"09\/06\/2008","documento":"N\/A","clave_institucion":18474,"url_info":"http:\/\/portaltransparencia.gob.mx\/pot\/contrataciones\/consultarContrato.do?method=consultaContrato&id.idContrato=2008001914&_idDependencia=18474"}