{"nombre_institucion":"INSTITUTO MEXICANO DEL PETROLEO","sector_presupuestal":"Energ\u00eda","siglas":"IMP","fecha_actualizacion":"08\/07\/2014","numero_contrato":"2008001547","unidad_administrativa":"DIRECTOR REGIONAL NORTE","procedimiento_contratacion":"ADJUDICACION DIRECTA","denominacion_asignado":"ESTRADA INFANTE SANTOS ADALBERTO","fecha_contrato":"22\/04\/2008","objeto_contrato":"B19125P8 SE REQUIERE LA CONTRATACION DE UN SERVICIO PARA IMPARTIR EL CURSO B19125P8 TCII OPERADOR CAMPOS PETROLEROS MATERIA: METODOS Y MEDICION DEL TRABAJO FECHA: 22-24 ABRIL 2008","monto_contrato":"$4248","moneda":"PESOS","fecha_inicio":"22\/04\/2008","fecha_fin":"24\/04\/2008","documento":"N\/A","clave_institucion":18474,"url_info":"http:\/\/portaltransparencia.gob.mx\/pot\/contrataciones\/consultarContrato.do?method=consultaContrato&id.idContrato=2008001547&_idDependencia=18474"}