{"nombre_institucion":"INSTITUTO MEXICANO DEL PETROLEO","sector_presupuestal":"Energ\u00eda","siglas":"IMP","fecha_actualizacion":"08\/07\/2014","numero_contrato":"2008001645","unidad_administrativa":"DIRECTOR CORPORATIVO DE FINANZAS Y ADMINISTRACION","procedimiento_contratacion":"OTROS","denominacion_asignado":"CASTILLO RODRIGUEZ BERNABE","fecha_contrato":"07\/05\/2008","objeto_contrato":"MATRAZ DE RAPIDA CONGELACION DE 80 ML. INCLUYE FRASCO Y TAPA PARA AD APTADOR DE 1\/2&quot; DE DIAMETRO, DIMENSIONES: 115 MM. H X 34 MM ID. (EQUIVALENTE A CPI03353-01), LAC 75402-0. MARCA LABCONCO, CATALOGO LAC-75402-00","monto_contrato":"$26342","moneda":"PESOS","fecha_inicio":"07\/05\/2008","fecha_fin":"04\/09\/2008","documento":"N\/A","clave_institucion":18474,"url_info":"http:\/\/portaltransparencia.gob.mx\/pot\/contrataciones\/consultarContrato.do?method=consultaContrato&id.idContrato=2008001645&_idDependencia=18474"}