{"nombre_institucion":"INSTITUTO MEXICANO DEL PETROLEO","sector_presupuestal":"Energ\u00eda","siglas":"IMP","fecha_actualizacion":"08\/07\/2014","numero_contrato":"2008000567","unidad_administrativa":"DIRECTOR REGIONAL NORTE","procedimiento_contratacion":"ADJUDICACION DIRECTA","denominacion_asignado":"GARZA MORENO GABRIELA","fecha_contrato":"28\/02\/2008","objeto_contrato":"SUSTITUTO DE CREMA P\/CAFE  453 GRS COFEE-MATE.","monto_contrato":"$4528.4","moneda":"PESOS","fecha_inicio":"28\/02\/2008","fecha_fin":"04\/03\/2008","documento":"N\/A","clave_institucion":18474,"url_info":"http:\/\/portaltransparencia.gob.mx\/pot\/contrataciones\/consultarContrato.do?method=consultaContrato&id.idContrato=2008000567&_idDependencia=18474"}