{"nombre_institucion":"PETR\u00d3LEOS MEXICANOS (CORPORATIVO) en proceso de reestructuraci\u00f3n","sector_presupuestal":"Energ\u00eda","siglas":"PEMEX","fecha_actualizacion":"18\/07\/2014","numero_contrato":"4200129280","unidad_administrativa":"SUBDIRECCI\u00d3N DE SERVICIOS DE SALUD","procedimiento_contratacion":"ADJUDICACION DIRECTA","denominacion_asignado":"MATERIALES MEDICOS Y QUIRURGICOS DE TABASCO, S.A. DE C.V.","fecha_contrato":"24\/02\/2014","objeto_contrato":"BARRERA PLANA P\/OSTOMIA CON ARO 70mm","monto_contrato":"$8868","moneda":"PESOS","fecha_inicio":"07\/03\/2014","fecha_fin":"07\/03\/2014","documento":"N\/A","clave_institucion":18572,"url_info":"http:\/\/portaltransparencia.gob.mx\/pot\/contrataciones\/consultarContrato.do?method=consultaContrato&id.idContrato=4200129280&_idDependencia=18572","_id":{"$id":"53d676fd4d5fa3ea4c8b5079"}}